alphascreen/__init__.py
alphascreen/__main__.py
alphascreen/analyze.py
alphascreen/argparser.py
alphascreen/decisiontree.py
alphascreen/jobsetup.py
alphascreen-1.19.dist-info/LICENSE
alphascreen-1.19.dist-info/METADATA
alphascreen-1.19.dist-info/WHEEL
alphascreen-1.19.dist-info/entry_points.txt
alphascreen-1.19.dist-info/top_level.txt
alphascreen-1.19.dist-info/RECORD
